knada_gsm/__init__.py
knada_gsm/api.py
knada_gsm-0.1.2.dist-info/LICENSE
knada_gsm-0.1.2.dist-info/WHEEL
knada_gsm-0.1.2.dist-info/METADATA
knada_gsm-0.1.2.dist-info/RECORD
