Metadata-Version: 2.1
Name: knada-gsm
Version: 0.1.2
Summary: 
Author: nada
Author-email: nada@nav.no
Requires-Python: >=3.8,<4.0
Classifier: Programming Language :: Python :: 3
Classifier: Programming Language :: Python :: 3.8
Classifier: Programming Language :: Python :: 3.9
Classifier: Programming Language :: Python :: 3.10
Classifier: Programming Language :: Python :: 3.11
Requires-Dist: google-cloud-secret-manager (>=2.12.5,<3.0.0)
